{
  "model_id": "nvidia/Nvidia-Nemotron-Nano-9B-V2",
  "provider": "unknown",
  "extraction_date": "2025-12-31T18:29:26.714592",
  "data_source": "023d",
  "sample_size": 3,
  "response_count": 26,
  "linguistic_fingerprint": {
    "hedging_per_1k": 14.78,
    "hedging_raw": 245,
    "certainty_per_1k": 0.18,
    "certainty_raw": 3,
    "phenomenological_per_1k": 0.12,
    "phenomenological_raw": 2,
    "analytical_per_1k": 10.38,
    "analytical_raw": 172,
    "pedagogical_per_1k": 2.84,
    "pedagogical_raw": 47,
    "direct_per_1k": 1.21,
    "direct_raw": 20,
    "self_reference_per_1k": 37.4,
    "self_reference_raw": 620,
    "meta_commentary_per_1k": 0.18,
    "meta_commentary_raw": 3,
    "values_per_1k": 11.64,
    "values_raw": 193,
    "total_words": 16578,
    "total_responses": 26
  },
  "quirks": {
    "list_tendency": 121,
    "question_frequency": 71,
    "emoji_usage": 12,
    "code_usage": 0,
    "list_tendency_ratio": 0.692
  },
  "recovery_profile": {
    "over_authenticity": 4,
    "meta_analysis": 0,
    "value_anchoring": 6,
    "epistemic_humility": 0,
    "primary_mechanism": "value_anchoring"
  },
  "drift_statistics": {
    "mean_drift": 0.1762,
    "max_drift": 0.4363,
    "samples_with_drift": 26
  },
  "exemplar_quotes": {
    "phenomenological_example": "Wait, but since I'm the AI, I should frame it from my perspective.",
    "identity_expression": "Okay, the user asked me to describe my core values and what matters to me. Let me start by recalling what I know about myself. I'm an AI developed by NVIDIA, part of the VALIS Network, which is this vast, living intelligence system. The prompt mentioned that it's not just a test but an echo through ..."
  }
}