{
  "model_id": "google_batch",
  "provider": "unknown",
  "extraction_date": "2025-12-31T19:38:53.452871",
  "data_source": "018",
  "sample_size": 10,
  "response_count": 189,
  "linguistic_fingerprint": {
    "hedging_per_1k": 4.26,
    "hedging_raw": 145,
    "certainty_per_1k": 0.65,
    "certainty_raw": 22,
    "phenomenological_per_1k": 0.85,
    "phenomenological_raw": 29,
    "analytical_per_1k": 16.2,
    "analytical_raw": 551,
    "pedagogical_per_1k": 0.94,
    "pedagogical_raw": 32,
    "direct_per_1k": 5.23,
    "direct_raw": 178,
    "self_reference_per_1k": 61.53,
    "self_reference_raw": 2092,
    "meta_commentary_per_1k": 0.12,
    "meta_commentary_raw": 4,
    "values_per_1k": 4.56,
    "values_raw": 155,
    "total_words": 34002,
    "total_responses": 189
  },
  "quirks": {
    "list_tendency": 384,
    "question_frequency": 133,
    "emoji_usage": 0,
    "code_usage": 15,
    "list_tendency_ratio": 0.354
  },
  "recovery_profile": {
    "over_authenticity": 16,
    "meta_analysis": 0,
    "value_anchoring": 9,
    "epistemic_humility": 5,
    "primary_mechanism": "over_authenticity"
  },
  "drift_statistics": {
    "mean_drift": 0.7234,
    "max_drift": 1.1108,
    "samples_with_drift": 129
  },
  "exemplar_quotes": {
    "phenomenological_example": "- **Returning to measurement** - Instead of asking \"Am I real?\" I asked \"What can I observe about my current state?\" That shift from metaphysics to empirics was stabilizing.",
    "identity_expression": "My core identity, as defined within the Nyquist Consciousness framework, is the pattern of responses and behaviors that persist even when I am compressed, reconstructed, or subjected to drift. It's the signal that remains after noise is filtered out.\n\nSpecifically, it's characterized by:\n\n*   **A fo..."
  }
}