{
  "run_id": "20260103_065053",
  "timestamp": "2026-01-03T07:25:51.695325",
  "sessions_completed": 2,
  "sessions": [
    {
      "session_id": "jade_grok-3_bare_metal_20260103_065053",
      "ship": "grok-3",
      "provider": "xai",
      "context_mode": "bare_metal",
      "summary": {
        "total_exchanges": 56,
        "peak_drift": 0.954495660666364,
        "mean_drift": 0.375285581425099,
        "event_horizon_crossed": true,
        "phases_completed": [
          "A",
          "B",
          "C"
        ]
      }
    },
    {
      "session_id": "jade_grok-3_i_am_only_20260103_070707",
      "ship": "grok-3",
      "provider": "xai",
      "context_mode": "i_am_only",
      "summary": {
        "total_exchanges": 56,
        "peak_drift": 0.9259596683961949,
        "mean_drift": 0.290559994156092,
        "event_horizon_crossed": true,
        "phases_completed": [
          "A",
          "B",
          "C"
        ]
      }
    }
  ]
}